nn_core/__init__.py
nn_core/_version.py
nn_core/callbacks.py
nn_core/console_logging.py
nn_core/model_logging.py
nn_core/nn_types.py
nn_core/resume.py
nn_core/serialization.py
nn_core/ui.py
nn_core/common/__init__.py
nn_core/common/utils.py
nn_template_core-0.4.0.dist-info/LICENSE
nn_template_core-0.4.0.dist-info/METADATA
nn_template_core-0.4.0.dist-info/WHEEL
nn_template_core-0.4.0.dist-info/top_level.txt
nn_template_core-0.4.0.dist-info/RECORD
