Metadata-Version: 2.1
Name: nn-template-core
Version: 0.4.0
Summary: Utility library for nn-template.
Home-page: https://github.com/grok-ai/nn-template-core
Author: Valentino Maiorca
Author-email: valentino@maiorca.xyz
License: MIT License
Keywords: python,torch
License-File: LICENSE
Requires-Dist: lightning ==2.0.*
Requires-Dist: hydra-core
Requires-Dist: wandb
Requires-Dist: python-dotenv
Requires-Dist: stqdm
Requires-Dist: rich
Provides-Extra: dev
Requires-Dist: black ; extra == 'dev'
Requires-Dist: flake8 ; extra == 'dev'
Requires-Dist: isort ; extra == 'dev'
Requires-Dist: pre-commit ; extra == 'dev'
Requires-Dist: bandit ; extra == 'dev'
Requires-Dist: pytest ; extra == 'dev'
Requires-Dist: pytest-cov ; extra == 'dev'
Provides-Extra: test
Requires-Dist: pytest ; extra == 'test'
Requires-Dist: pytest-cov ; extra == 'test'
